{
  "document_id": "2013-NCDOT-Annual-Erosion-and-Sedimentation-Control-Report-FINAL",
  "source_file": "source.pdf",
  "success": true,
  "error": null,
  "confidence_score": 0.97,
  "routing_decision": "flag_for_review",
  "edge_case_flags": [
    "image_resolution_issue",
    "table_extraction_mismatch"
  ],
  "metrics": {
    "total_duration_ms": 130637,
    "extraction_ms": 857,
    "conversion_ms": 129726
  },
  "extraction_baseline": {
    "word_count": 2712,
    "image_count": 19,
    "table_count": 7
  },
  "gemini_counts": {
    "word_count": 1812,
    "image_count": 18,
    "table_count": 3
  }
}