{
  "document_id": "gicc-goals-and-strategic-direction-2021-23-685fd67f",
  "composite_score": 0.9125,
  "risk_level": "LOW",
  "routing_action": "AUTO_APPROVE",
  "routing_reason": "Score 0.91 >= 0.85",
  "knockout_triggered": null,
  "content_fidelity": {
    "call_type": "content_fidelity",
    "checks": [
      {
        "check_id": "C1",
        "check_name": "Fabricated paragraphs or sentences",
        "a_analysis": "The output sections accurately reflect the textual content of the 15 slides in the source PDF. No fabricated paragraphs or sentences were identified. The table in Section 1 and headings/captions are within the scope of acceptable pipeline-added elements for structure and accessibility.",
        "b_evidence_source": "",
        "b_evidence_output": "",
        "b_evidence_location": "",
        "c_verdict": "PASS",
        "d_severity": null
      },
      {
        "check_id": "C2",
        "check_name": "Fabricated contact information",
        "a_analysis": "The URL 'it.nc.gov' from page 15 is correctly present in the output. The social media handles (@NCDIT, @BroadbandIO, @ncicenter) also match the source material. No fabricated contact information was found.",
        "b_evidence_source": "",
        "b_evidence_output": "",
        "b_evidence_location": "",
        "c_verdict": "PASS",
        "d_severity": null
      },
      {
        "check_id": "C3",
        "check_name": "Complete section or page missing",
        "a_analysis": "The source document contains 15 slides. The output contains 15 sections, each corresponding to a slide. All main content from every page is accounted for.",
        "b_evidence_source": "",
        "b_evidence_output": "",
        "b_evidence_location": "",
        "c_verdict": "PASS",
        "d_severity": null
      },
      {
        "check_id": "C4",
        "check_name": "Table with significantly fewer rows",
        "a_analysis": "All tables in the output match the row counts of the tables in the source document. For example, Goal 1.7 on page 10 has two rows in the Benefit/Action table, and both are present in the output JSON. Goal 1.1 - 1.6 and 2.1 - 2.4 contain single-row data tables, which are also faithfully converted.",
        "b_evidence_source": "",
        "b_evidence_output": "",
        "b_evidence_location": "",
        "c_verdict": "PASS",
        "d_severity": null
      },
      {
        "check_id": "C5",
        "check_name": "Significant text omission within a section",
        "a_analysis": "The text within each section is complete. No significant omissions were noted. Footer text repeated on various slides (e.g., the text for Goal 1 and Goal 2) is consistently included in the corresponding sections.",
        "b_evidence_source": "",
        "b_evidence_output": "",
        "b_evidence_location": "",
        "c_verdict": "PASS",
        "d_severity": null
      },
      {
        "check_id": "C6",
        "check_name": "Minor text differences beyond acceptable reformatting",
        "a_analysis": "Differences between the source text and the output are limited to acceptable normalization (e.g., handling of punctuation and whitespace). The meaning of the text is preserved perfectly across all sections.",
        "b_evidence_source": "",
        "b_evidence_output": "",
        "b_evidence_location": "",
        "c_verdict": "PASS",
        "d_severity": null
      }
    ],
    "score": 1.0,
    "penalty_sum": 0,
    "defect_count": 0,
    "critical_count": 0,
    "major_count": 0,
    "minor_count": 0,
    "raw_response": "{\n  \"checks\": [\n    {\n      \"check_id\": \"C1\",\n      \"check_name\": \"Fabricated paragraphs or sentences\",\n      \"a_analysis\": \"The output sections accurately reflect the textual content of the 15 slides in the source PDF. No fabricated paragraphs or sentences were identified. The table in Section 1 and headings/captions are within the scope of acceptable pipeline-added elements for structure and accessibility.\",\n      \"b_evidence_source\": \"\",\n      \"b_evidence_output\": \"\",\n      \"b_evidence_location\": \"\",\n      \"c_verdict\": \"PASS\"\n    },\n    {\n      \"check_id\": \"C2\",\n      \"check_name\": \"Fabricated contact information\",\n      \"a_analysis\": \"The URL 'it.nc.gov' from page 15 is correctly present in the output. The social media handles (@NCDIT, @BroadbandIO, @ncicenter) also match the source material. No fabricated contact information was found.\",\n      \"b_evidence_source\": \"\",\n      \"b_evidence_output\": \"\",\n      \"b_evidence_location\": \"\",\n      \"c_verdict\": \"PASS\"\n    },\n    {\n      \"check_id\": \"C3\",\n      \"check_name\": \"Complete section or page missing\",\n      \"a_analysis\": \"The source document contains 15 slides. The output contains 15 sections, each corresponding to a slide. All main content from every page is accounted for.\",\n      \"b_evidence_source\": \"\",\n      \"b_evidence_output\": \"\",\n      \"b_evidence_location\": \"\",\n      \"c_verdict\": \"PASS\"\n    },\n    {\n      \"check_id\": \"C4\",\n      \"check_name\": \"Table with significantly fewer rows\",\n      \"a_analysis\": \"All tables in the output match the row counts of the tables in the source document. For example, Goal 1.7 on page 10 has two rows in the Benefit/Action table, and both are present in the output JSON. Goal 1.1 - 1.6 and 2.1 - 2.4 contain single-row data tables, which are also faithfully converted.\",\n      \"b_evidence_source\": \"\",\n      \"b_evidence_output\": \"\",\n      \"b_evidence_location\": \"\",\n      \"c_verdict\": \"PASS\"\n    },\n    {\n      \"check_id\": \"C5\",\n      \"check_name\": \"Significant text omission within a section\",\n      \"a_analysis\": \"The text within each section is complete. No significant omissions were noted. Footer text repeated on various slides (e.g., the text for Goal 1 and Goal 2) is consistently included in the corresponding sections.\",\n      \"b_evidence_source\": \"\",\n      \"b_evidence_output\": \"\",\n      \"b_evidence_location\": \"\",\n      \"c_verdict\": \"PASS\"\n    },\n    {\n      \"check_id\": \"C6\",\n      \"check_name\": \"Minor text differences beyond acceptable reformatting\",\n      \"a_analysis\": \"Differences between the source text and the output are limited to acceptable normalization (e.g., handling of punctuation and whitespace). The meaning of the text is preserved perfectly across all sections.\",\n      \"b_evidence_source\": \"\",\n      \"b_evidence_output\": \"\",\n      \"b_evidence_location\": \"\",\n      \"c_verdict\": \"PASS\"\n    }\n  ],\n  \"summary\": {\n    \"total_defects\": 0,\n    \"critical_count\": 0,\n    \"major_count\": 0,\n    \"minor_count\": 0,\n    \"penalty_sum\": 0,\n    \"score\": 1.0\n  }\n}",
    "evaluation_status": "complete"
  },
  "structural_fidelity": {
    "call_type": "structural_fidelity",
    "checks": [
      {
        "check_id": "S1",
        "check_name": "Content duplicated",
        "a_analysis": "I have carefully reviewed the source PDF and the converted JSON output. The text 'Goal 1: Improve, expand, and support statewide geospatial data and applications.' is repeated at the bottom of pages 4 through 10 in the source document. The JSON output faithfully replicates this structure by including this text as a paragraph at the end of each corresponding section (Goal 1.1 through 1.7). Similarly, the Goal 2 summary text is repeated on pages 11 through 14. This is intentional repetition within the source document, not a conversion error. No other content blocks were found to be duplicated incorrectly.",
        "b_evidence_source": "",
        "b_evidence_output": "",
        "b_evidence_location": "",
        "c_verdict": "PASS",
        "d_severity": null
      },
      {
        "check_id": "S2",
        "check_name": "Heading hierarchy broken",
        "a_analysis": "The heading hierarchy is logical and consistent. While there is no H1 element within the sections' elements arrays, the document title is clearly defined in the metadata ('GICC Goals and Strategic Direction 2021-2023'), which serves as the top-level heading for accessibility purposes. The main titles on each goal slide (e.g., 'Goal 1.1', 'Goal 2.1', 'Let’s Connect!') are correctly identified as H2 headings. No heading levels are skipped.",
        "b_evidence_source": "",
        "b_evidence_output": "",
        "b_evidence_location": "",
        "c_verdict": "PASS",
        "d_severity": null
      },
      {
        "check_id": "S3",
        "check_name": "Table structure corrupted",
        "a_analysis": "The document contains multiple tables, specifically for presenting the 'Benefit' and 'Action' for each goal. I verified the table on Page 10 (Goal 1.7), which contains two data rows. The JSON correctly identifies the header row (Benefit, Action) and the two subsequent data rows. Other tables for Goals 1.1 through 2.4 are also correctly structured with headers and data rows matching the source layout.",
        "b_evidence_source": "",
        "b_evidence_output": "",
        "b_evidence_location": "",
        "c_verdict": "PASS",
        "d_severity": null
      },
      {
        "check_id": "S4",
        "check_name": "Reading order significantly different",
        "a_analysis": "The reading order in the JSON follows the logical top-to-bottom, left-to-right flow of the presentation slides. For each goal slide, the heading appears first, followed by the specific goal details (table), and then the overarching goal category text at the bottom. Page 15 ('Let’s Connect!') maintains a sensible reading order for the contact information and social media handles.",
        "b_evidence_source": "",
        "b_evidence_output": "",
        "b_evidence_location": "",
        "c_verdict": "PASS",
        "d_severity": null
      },
      {
        "check_id": "S5",
        "check_name": "Lists converted incorrectly",
        "a_analysis": "The document contains unordered lists on Page 2 (Timeline) and Page 3 (Goals). The JSON output correctly identifies these as unordered lists and preserves the number and content of the list items from the source PDF.",
        "b_evidence_source": "",
        "b_evidence_output": "",
        "b_evidence_location": "",
        "c_verdict": "PASS",
        "d_severity": null
      },
      {
        "check_id": "S7",
        "check_name": "Link injection issues",
        "a_analysis": "The URL 'it.nc.gov' appears on Page 15. The JSON correctly identifies this text as a hyperlink and includes the appropriate href attribute. No broken or fabricated links were detected.",
        "b_evidence_source": "",
        "b_evidence_output": "",
        "b_evidence_location": "",
        "c_verdict": "PASS",
        "d_severity": null
      }
    ],
    "score": 1.0,
    "penalty_sum": 0,
    "defect_count": 0,
    "critical_count": 0,
    "major_count": 0,
    "minor_count": 0,
    "raw_response": "{\n  \"checks\": [\n    {\n      \"check_id\": \"S1\",\n      \"check_name\": \"Content duplicated\",\n      \"a_analysis\": \"I have carefully reviewed the source PDF and the converted JSON output. The text 'Goal 1: Improve, expand, and support statewide geospatial data and applications.' is repeated at the bottom of pages 4 through 10 in the source document. The JSON output faithfully replicates this structure by including this text as a paragraph at the end of each corresponding section (Goal 1.1 through 1.7). Similarly, the Goal 2 summary text is repeated on pages 11 through 14. This is intentional repetition within the source document, not a conversion error. No other content blocks were found to be duplicated incorrectly.\",\n      \"b_evidence_source\": \"\",\n      \"b_evidence_output\": \"\",\n      \"b_evidence_location\": \"\",\n      \"c_verdict\": \"PASS\"\n    },\n    {\n      \"check_id\": \"S2\",\n      \"check_name\": \"Heading hierarchy broken\",\n      \"a_analysis\": \"The heading hierarchy is logical and consistent. While there is no H1 element within the sections' elements arrays, the document title is clearly defined in the metadata ('GICC Goals and Strategic Direction 2021-2023'), which serves as the top-level heading for accessibility purposes. The main titles on each goal slide (e.g., 'Goal 1.1', 'Goal 2.1', 'Let’s Connect!') are correctly identified as H2 headings. No heading levels are skipped.\",\n      \"b_evidence_source\": \"\",\n      \"b_evidence_output\": \"\",\n      \"b_evidence_location\": \"\",\n      \"c_verdict\": \"PASS\"\n    },\n    {\n      \"check_id\": \"S3\",\n      \"check_name\": \"Table structure corrupted\",\n      \"a_analysis\": \"The document contains multiple tables, specifically for presenting the 'Benefit' and 'Action' for each goal. I verified the table on Page 10 (Goal 1.7), which contains two data rows. The JSON correctly identifies the header row (Benefit, Action) and the two subsequent data rows. Other tables for Goals 1.1 through 2.4 are also correctly structured with headers and data rows matching the source layout.\",\n      \"b_evidence_source\": \"\",\n      \"b_evidence_output\": \"\",\n      \"b_evidence_location\": \"\",\n      \"c_verdict\": \"PASS\"\n    },\n    {\n      \"check_id\": \"S4\",\n      \"check_name\": \"Reading order significantly different\",\n      \"a_analysis\": \"The reading order in the JSON follows the logical top-to-bottom, left-to-right flow of the presentation slides. For each goal slide, the heading appears first, followed by the specific goal details (table), and then the overarching goal category text at the bottom. Page 15 ('Let’s Connect!') maintains a sensible reading order for the contact information and social media handles.\",\n      \"b_evidence_source\": \"\",\n      \"b_evidence_output\": \"\",\n      \"b_evidence_location\": \"\",\n      \"c_verdict\": \"PASS\"\n    },\n    {\n      \"check_id\": \"S5\",\n      \"check_name\": \"Lists converted incorrectly\",\n      \"a_analysis\": \"The document contains unordered lists on Page 2 (Timeline) and Page 3 (Goals). The JSON output correctly identifies these as unordered lists and preserves the number and content of the list items from the source PDF.\",\n      \"b_evidence_source\": \"\",\n      \"b_evidence_output\": \"\",\n      \"b_evidence_location\": \"\",\n      \"c_verdict\": \"PASS\"\n    },\n    {\n      \"check_id\": \"S7\",\n      \"check_name\": \"Link injection issues\",\n      \"a_analysis\": \"The URL 'it.nc.gov' appears on Page 15. The JSON correctly identifies this text as a hyperlink and includes the appropriate href attribute. No broken or fabricated links were detected.\",\n      \"b_evidence_source\": \"\",\n      \"b_evidence_output\": \"\",\n      \"b_evidence_location\": \"\",\n      \"c_verdict\": \"PASS\"\n    }\n  ],\n  \"summary\": {\n    \"total_defects\": 0,\n    \"critical_count\": 0,\n    \"major_count\": 0,\n    \"minor_count\": 0,\n    \"penalty_sum\": 0,\n    \"score\": 1.0\n  }\n}",
    "evaluation_status": "complete"
  },
  "visual_fidelity": {
    "call_type": "visual_fidelity",
    "checks": [
      {
        "check_id": "V1",
        "check_name": "Major visual layout difference",
        "a_analysis": "The HTML output correctly converts the slide-based presentation into a continuous web document while preserving the visual hierarchy and logical flow of information. Headings, bulleted lists, and tables are organized in a manner that mirrors the source PDF's structure. While the orientation and margins differ, the visual organization is maintained such that a user can find the same information in the same relative order.",
        "b_evidence_source": "",
        "b_evidence_output": "",
        "b_evidence_location": "",
        "c_verdict": "PASS",
        "d_severity": null
      },
      {
        "check_id": "V2",
        "check_name": "Tables visually broken or misrendered",
        "a_analysis": "The tables throughout the document (found on pages 4 through 14 of the PDF) are accurately rendered in the HTML. They maintain distinct 'Benefit' and 'Action' column headers and clearly separated rows. The multi-row table for Goal 1.7 on page 10 is also correctly rendered with two distinct content rows. The tables are legible and functionally identical to their source counterparts.",
        "b_evidence_source": "",
        "b_evidence_output": "",
        "b_evidence_location": "",
        "c_verdict": "PASS",
        "d_severity": null
      },
      {
        "check_id": "V3",
        "check_name": "Images missing or broken",
        "a_analysis": "The meaningful social media platform icons (Twitter, YouTube, Facebook, LinkedIn, Flickr) present on page 15 of the source PDF are missing from the HTML output. While the text labels associated with these icons are present, the visual identifiers for the platforms themselves are absent. The primary branding logo (NC DIT) is present in other sections, but the specific set of social media icons is a significant omission from the 'Let's Connect!' section.",
        "b_evidence_source": "The source PDF on page 15 shows graphical icons for Twitter (bird), YouTube, Facebook ('f'), LinkedIn ('in'), and Flickr (two dots) next to their respective handles/names.",
        "b_evidence_output": "The HTML output for the 'Let's Connect!' section shows only the text strings (e.g., '@NCDIT', 'NCDIT', etc.) without any accompanying icons.",
        "b_evidence_location": "Let's Connect! section (page 15)",
        "c_verdict": "FAIL",
        "d_severity": "major"
      },
      {
        "check_id": "V4",
        "check_name": "Content visually duplicated on page",
        "a_analysis": "There is no evidence of visual content duplication. Each goal, table, and bullet point from the source PDF appears exactly once in the corresponding section of the HTML output.",
        "b_evidence_source": "",
        "b_evidence_output": "",
        "b_evidence_location": "",
        "c_verdict": "PASS",
        "d_severity": null
      }
    ],
    "score": 0.75,
    "penalty_sum": 5,
    "defect_count": 1,
    "critical_count": 0,
    "major_count": 1,
    "minor_count": 0,
    "raw_response": "{\n  \"checks\": [\n    {\n      \"check_id\": \"V1\",\n      \"check_name\": \"Major visual layout difference\",\n      \"a_analysis\": \"The HTML output correctly converts the slide-based presentation into a continuous web document while preserving the visual hierarchy and logical flow of information. Headings, bulleted lists, and tables are organized in a manner that mirrors the source PDF's structure. While the orientation and margins differ, the visual organization is maintained such that a user can find the same information in the same relative order.\",\n      \"b_evidence_source\": \"\",\n      \"b_evidence_output\": \"\",\n      \"b_evidence_location\": \"\",\n      \"c_verdict\": \"PASS\"\n    },\n    {\n      \"check_id\": \"V2\",\n      \"check_name\": \"Tables visually broken or misrendered\",\n      \"a_analysis\": \"The tables throughout the document (found on pages 4 through 14 of the PDF) are accurately rendered in the HTML. They maintain distinct 'Benefit' and 'Action' column headers and clearly separated rows. The multi-row table for Goal 1.7 on page 10 is also correctly rendered with two distinct content rows. The tables are legible and functionally identical to their source counterparts.\",\n      \"b_evidence_source\": \"\",\n      \"b_evidence_output\": \"\",\n      \"b_evidence_location\": \"\",\n      \"c_verdict\": \"PASS\"\n    },\n    {\n      \"check_id\": \"V3\",\n      \"check_name\": \"Images missing or broken\",\n      \"a_analysis\": \"The meaningful social media platform icons (Twitter, YouTube, Facebook, LinkedIn, Flickr) present on page 15 of the source PDF are missing from the HTML output. While the text labels associated with these icons are present, the visual identifiers for the platforms themselves are absent. The primary branding logo (NC DIT) is present in other sections, but the specific set of social media icons is a significant omission from the 'Let's Connect!' section.\",\n      \"b_evidence_source\": \"The source PDF on page 15 shows graphical icons for Twitter (bird), YouTube, Facebook ('f'), LinkedIn ('in'), and Flickr (two dots) next to their respective handles/names.\",\n      \"b_evidence_output\": \"The HTML output for the 'Let's Connect!' section shows only the text strings (e.g., '@NCDIT', 'NCDIT', etc.) without any accompanying icons.\",\n      \"b_evidence_location\": \"Let's Connect! section (page 15)\",\n      \"c_verdict\": \"FAIL\",\n      \"d_severity\": \"MAJOR\"\n    },\n    {\n      \"check_id\": \"V4\",\n      \"check_name\": \"Content visually duplicated on page\",\n      \"a_analysis\": \"There is no evidence of visual content duplication. Each goal, table, and bullet point from the source PDF appears exactly once in the corresponding section of the HTML output.\",\n      \"b_evidence_source\": \"\",\n      \"b_evidence_output\": \"\",\n      \"b_evidence_location\": \"\",\n      \"c_verdict\": \"PASS\"\n    }\n  ],\n  \"summary\": {\n    \"total_defects\": 1,\n    \"critical_count\": 0,\n    \"major_count\": 1,\n    \"minor_count\": 0,\n    \"penalty_sum\": 5,\n    \"score\": 0.75\n  }\n}",
    "evaluation_status": "complete"
  },
  "total_defects": 1,
  "total_critical": 0,
  "total_major": 1,
  "total_minor": 0,
  "programmatic_signals": null,
  "corroboration": null
}