{
  "document_id": "17-APRFY2015.pdf",
  "source_file": "source.pdf",
  "success": true,
  "error": null,
  "confidence_score": 0.94,
  "routing_decision": "needs_retry",
  "edge_case_flags": [
    "complex_tables",
    "image_resolution_issue",
    "chunk_conversion_failure"
  ],
  "metrics": {
    "total_duration_ms": 1176418,
    "extraction_ms": 5181,
    "conversion_ms": 1171172
  },
  "extraction_baseline": {
    "word_count": 23198,
    "image_count": 0,
    "table_count": 66
  },
  "gemini_counts": {
    "word_count": 13945,
    "image_count": 11,
    "table_count": 46
  }
}