{
  "document_id": "scanned-from-paper-many-pages-of-tables-6878",
  "source_file": "source.pdf",
  "success": false,
  "error": "3/4 chunks failed (below 50% threshold): chunk 1 (pages 1-11): Completeness validation failed (score=73): Word count (437) is 9% of baseline (4650); chunk 2 (pages 11-21): Completeness validation failed (score=57): Last text may be truncated (ends with ' Subscription Prices'); Word count (276) is 6% of baseline (4347); chunk 3 (pages 21-31): Completeness validation failed (score=55): Last text may be truncated (ends with 'etual License Prices'); Word count (17) is 0% of baseline (4484)",
  "confidence_score": null,
  "routing_decision": null,
  "edge_case_flags": [],
  "metrics": {
    "total_duration_ms": 873200,
    "extraction_ms": 6645,
    "conversion_ms": 866555
  },
  "extraction_baseline": {
    "word_count": 15914,
    "image_count": 0,
    "table_count": 38
  }
}